setup.py
distributions_awofeko_BD/Binomialdistribution_challenge.py
distributions_awofeko_BD/Gaussiandistribution.py
distributions_awofeko_BD/Generaldistribution.py
distributions_awofeko_BD/__init__.py
distributions_awofeko_BD.egg-info/PKG-INFO
distributions_awofeko_BD.egg-info/SOURCES.txt
distributions_awofeko_BD.egg-info/dependency_links.txt
distributions_awofeko_BD.egg-info/not-zip-safe
distributions_awofeko_BD.egg-info/top_level.txt