Metadata-Version: 1.0
Name: distributions-awofeko-BD
Version: 1.2
Summary: Gaussian and Binomial Distributions and probability
Home-page: UNKNOWN
Author: MICHAEL AWOEFKO
Author-email: michaelawofeko@gmail.com
License: UNKNOWN
Platform: UNKNOWN
